MANIFEST.in
README.txt
setup.py
test.py
boois_creator/__init__.py
boois_creator/creator.py
boois_creator/test.py
boois_creator.egg-info/PKG-INFO
boois_creator.egg-info/SOURCES.txt
boois_creator.egg-info/dependency_links.txt
boois_creator.egg-info/top_level.txt
boois_creator.egg-info/zip-safe
boois_creator/core/__init__.py
boois_creator/core/info/__init__.py
boois_creator/core/info/field.py
boois_creator/core/info/obj.py
boois_creator/core/info/task.py
boois_creator/demo/__init__.py
boois_creator/demo/genner_client.py
boois_creator/demo/json_checker_client.py
boois_creator/tpl/__init__.py
boois_creator/utils/__init__.py
boois_creator/utils/cmd_parser.py
boois_creator/utils/enum_parser.py
boois_creator/utils/obj_json_checker.py
boois_creator/utils/obj_json_parser.py
boois_creator/utils/str_fmt_helper.py
boois_creator/utils/tpl_filename_parser.py
boois_creator/utils/vali_rule_chker.py
boois_creator/utils/vali_rule_info.py
boois_creator/utils/table_struc_creator/__init__.py
boois_creator/utils/table_struc_creator/factory.py
boois_creator/utils/table_struc_creator/field.py
boois_creator/utils/table_struc_creator/table.py