Metadata-Version: 1.1
Name: boois-creator
Version: 1.0.15
Summary: boois_creator
Home-page: http://www.boois.cn/
Author: boois
Author-email: admin@boois.cn
License: MIT
Keywords: boois_creator
Platform: UNKNOWN
Classifier: License :: OSI Approved :: MIT License
Classifier: Programming Language :: Python
Classifier: Intended Audience :: Developers
Classifier: Operating System :: OS Independent
